waccy_edgar/__init__.py
waccy_edgar/extractor.py
waccy_edgar-0.0.2.dist-info/METADATA
waccy_edgar-0.0.2.dist-info/WHEEL
waccy_edgar-0.0.2.dist-info/entry_points.txt
waccy_edgar-0.0.2.dist-info/RECORD
