Metadata-Version: 2.4
Name: waccy-edgar
Version: 0.0.2
Summary: WACCY extension for SEC EDGAR filing parsing
Project-URL: Homepage, https://github.com/DecisionNerd/waccy
Project-URL: Repository, https://github.com/DecisionNerd/waccy
Project-URL: Issues, https://github.com/DecisionNerd/waccy/issues
Project-URL: Documentation, https://github.com/DecisionNerd/waccy#readme
Author: WACCY Contributors
License: MIT
Keywords: edgar,finance,financial-modeling,sec,waccy
Classifier: Development Status :: 2 - Pre-Alpha
Classifier: Intended Audience :: Financial and Insurance Industry
Classifier: License :: OSI Approved :: MIT License
Classifier: Programming Language :: Python :: 3.13
Classifier: Topic :: Office/Business :: Financial
Requires-Python: >=3.13
Requires-Dist: waccy>=0.0.2
Provides-Extra: dev
Requires-Dist: mypy>=1.13.0; extra == 'dev'
Requires-Dist: pytest>=9.0.2; extra == 'dev'
Requires-Dist: ruff>=0.8.0; extra == 'dev'
